OrcidNormalizer/__init__.py
OrcidNormalizer/main.py
OrcidNormalizer-0.0.1.dist-info/LICENSE
OrcidNormalizer-0.0.1.dist-info/METADATA
OrcidNormalizer-0.0.1.dist-info/WHEEL
OrcidNormalizer-0.0.1.dist-info/top_level.txt
OrcidNormalizer-0.0.1.dist-info/RECORD
