Metadata-Version: 2.1
Name: OrcidNormalizer
Version: 0.0.1
Summary: Tool no normalize orcids
Home-page: https://git.connect.dzd-ev.de/dzdpythonmodules/dzdutils
Author: JT
Author-email: justus.taeger@helmholtz-muenchen.de
License: MIT
Platform: UNKNOWN
Requires-Python: >=3.6
License-File: LICENSE
